MANIFEST.in
README
RELEASE-VERSION
get_git_version.py
setup.py
pymarietje.egg-info/PKG-INFO
pymarietje.egg-info/SOURCES.txt
pymarietje.egg-info/dependency_links.txt
pymarietje.egg-info/entry_points.txt
pymarietje.egg-info/requires.txt
pymarietje.egg-info/top_level.txt
src/__init__.py
src/cursesui.py
src/lstree.py
src/marietje.py
src/upload.py