Metadata-Version: 1.0
Name: pymarietje
Version: 0.1.0a2
Summary: Curses client for MarietjeD music daemon
Home-page: http://github.com/bwesterb/pymarietje/
Author: Bas Westerbaan
Author-email: bas@westerbaan.name
License: UNKNOWN
Platform: UNKNOWN
